moarchiving/__init__.py
moarchiving/__main__.py
moarchiving/constrained_moarchive.py
moarchiving/get_archive.py
moarchiving/moarchiving.py
moarchiving/moarchiving3obj.py
moarchiving/moarchiving4obj.py
moarchiving/moarchiving_parent.py
moarchiving/moarchiving_utils.py
moarchiving/test.py
moarchiving/tests/__init__.py
moarchiving/tests/point_sampling.py
moarchiving/tests/test_constrained_moarchiving.py
moarchiving/tests/test_moarchiving2obj.py
moarchiving/tests/test_moarchiving3obj.py
moarchiving/tests/test_moarchiving4obj.py
moarchiving/tests/test_sorted_list.py
moarchiving-1.0.0.dist-info/licenses/LICENSE
moarchiving-1.0.0.dist-info/METADATA
moarchiving-1.0.0.dist-info/WHEEL
moarchiving-1.0.0.dist-info/top_level.txt
moarchiving-1.0.0.dist-info/RECORD
