Metadata-Version: 2.4
Name: moarchiving
Version: 1.0.0
Summary: This package implements a non-dominated archive for 2, 3 or 4 objectives with hypervolume indicator and uncrowded hypervolume improvement computation.
Author: Nace Sever, Mila Nedic, Tea Tusar
Author-email: Nikolaus Hansen <authors_firstname.lastname@inria.fr>
Project-URL: Homepage, https://github.com/cma-es/moarchiving
Keywords: multi-objective,optimization
Classifier: Development Status :: 4 - Beta
Classifier: Environment :: Console
Classifier: Intended Audience :: Education
Classifier: Intended Audience :: Other Audience
Classifier: Intended Audience :: Science/Research
Classifier: Operating System :: OS Independent
Classifier: Programming Language :: Python :: 2.7
Classifier: Programming Language :: Python :: 3
Classifier: Topic :: Scientific/Engineering
Classifier: Topic :: Scientific/Engineering :: Artificial Intelligence
Classifier: Topic :: Scientific/Engineering :: Mathematics
License-File: LICENSE
Requires-Dist: sortedcontainers>=2.4.0
Provides-Extra: arbitrary-precision
Requires-Dist: fractions; extra == "arbitrary-precision"
Dynamic: license-file
